econ_layers/__init__.py
econ_layers/econ_layers.py
econ_layers/layers.py
econ_layers/utilities.py
econ_layers-0.0.28.dist-info/LICENSE
econ_layers-0.0.28.dist-info/METADATA
econ_layers-0.0.28.dist-info/WHEEL
econ_layers-0.0.28.dist-info/dependency_links.txt
econ_layers-0.0.28.dist-info/top_level.txt
econ_layers-0.0.28.dist-info/RECORD
