Metadata-Version: 2.1
Name: econ-layers
Version: 0.0.28
Summary: Pytorch layers for economic applications.
Home-page: https://github.com/HighDimensionalEconLab/econ_layers
Author: Jesse Perla
Author-email: jesseperla@gmail.com
License: MIT license
Keywords: econ_layers
Classifier: Development Status :: 2 - Pre-Alpha
Classifier: Intended Audience :: Developers
Classifier: License :: OSI Approved :: MIT License
Classifier: Natural Language :: English
Classifier: Programming Language :: Python :: 3
Classifier: Programming Language :: Python :: 3.5
Classifier: Programming Language :: Python :: 3.6
Classifier: Programming Language :: Python :: 3.7
Classifier: Programming Language :: Python :: 3.8
Requires-Python: >=3.8
License-File: LICENSE
Requires-Dist: torch (>=1.10)
Requires-Dist: pytest
Requires-Dist: black
Requires-Dist: numpy
Requires-Dist: jsonargparse[signatures] (>=4.19)
